standoffconverter/__init__.py
standoffconverter/base.py
standoffconverter/converters.py
standoffconverter/standoffs.py
standoffconverter/utils.py
standoffconverter/views.py
standoffconverter-0.8.11.dist-info/LICENSE
standoffconverter-0.8.11.dist-info/METADATA
standoffconverter-0.8.11.dist-info/WHEEL
standoffconverter-0.8.11.dist-info/top_level.txt
standoffconverter-0.8.11.dist-info/RECORD
